ixcom/__init__.py
ixcom/cmdline.py
ixcom/commands.py
ixcom/crc16.py
ixcom/data.py
ixcom/exceptions.py
ixcom/grep.py
ixcom/messages.py
ixcom/parameters.py
ixcom/parser.py
ixcom/protocol.py
ixcom-1.2.0.dist-info/LICENSE
ixcom-1.2.0.dist-info/METADATA
ixcom-1.2.0.dist-info/WHEEL
ixcom-1.2.0.dist-info/entry_points.txt
ixcom-1.2.0.dist-info/top_level.txt
ixcom-1.2.0.dist-info/RECORD
