Metadata-Version: 2.1
Name: ixcom
Version: 1.2.0
Summary: Library for communicating with xcom devices over network
Home-page: http://www.imar-navigation.de
Author: iMAR Navigation GmbH
Author-email: support@imar-navigation.de
License: UNKNOWN
Project-URL: Documentation, https://ixcom.readthedocs.io/en/latest/
Project-URL: Source Code, https://github.com/imar-navigation/ixcom-python
Keywords: XCOM,Inertial navigation,INS,iMAR,iNAT,GNSS,GPS,AHRS
Platform: UNKNOWN
Classifier: Programming Language :: Python :: 3.6
Classifier: License :: OSI Approved :: MIT License
Classifier: Operating System :: OS Independent
Requires-Dist: numpy (>=1.16.2)
